lionel/constants.py
lionel/model/base_model.py
lionel/model/bayesian/base_bayesian_model.py
lionel/model/bayesian/hierarchical_model.py
lionel/model/sklearn/.gitkeep
lionel/model/sklearn/base_sklearn_model.py
lionel/model/sklearn/naive.py
lionel/selector/core/base_selector.py
lionel/selector/fpl/xi_selector.py
lionel/selector/fpl/xv_selector.py
lionel/utils.py
lionel-0.1.1.dist-info/LICENSE
lionel-0.1.1.dist-info/METADATA
lionel-0.1.1.dist-info/WHEEL
lionel-0.1.1.dist-info/RECORD
