Metadata-Version: 2.1
Name: lionel
Version: 0.1.1
Summary: Predict fantasy player points and optimise the team
Home-page: https://github.com/jth500/lionel
License: MIT
Author: jth500
Author-email: jtobyh@gmail.com
Requires-Python: >=3.11,<4.0
Classifier: License :: OSI Approved :: MIT License
Classifier: Programming Language :: Python :: 3
Classifier: Programming Language :: Python :: 3.11
Classifier: Programming Language :: Python :: 3.12
Requires-Dist: arviz (==0.19.0)
Requires-Dist: numpy
Requires-Dist: pandas
Requires-Dist: pulp
Requires-Dist: pymc (>=5.0,<6.0)
Requires-Dist: pymc-marketing (>=0.9.0)
Requires-Dist: seaborn
Project-URL: Repository, https://github.com/jth500/lionel
